{
  "scene": "pine_clearing",
  "image_size": [
    1376,
    768
  ],
  "perches": [
    {
      "name": "ground_1",
      "x": 0,
      "y": 494,
      "type": "ground"
    },
    {
      "name": "rock_1",
      "x": 71,
      "y": 464,
      "type": "rock"
    },
    {
      "name": "rock_2",
      "x": 243,
      "y": 208,
      "type": "rock"
    },
    {
      "name": "ground_2",
      "x": 270,
      "y": 505,
      "type": "ground"
    },
    {
      "name": "ground_3",
      "x": 540,
      "y": 485,
      "type": "ground"
    }
  ],
  "ground_polygon": [
    [
      0,
      494
    ],
    [
      45,
      548
    ],
    [
      90,
      547
    ],
    [
      135,
      496
    ],
    [
      180,
      495
    ],
    [
      225,
      509
    ],
    [
      270,
      505
    ],
    [
      315,
      485
    ],
    [
      360,
      484
    ],
    [
      405,
      481
    ],
    [
      450,
      481
    ],
    [
      495,
      483
    ],
    [
      540,
      485
    ],
    [
      585,
      628
    ],
    [
      630,
      670
    ],
    [
      675,
      646
    ],
    [
      720,
      649
    ],
    [
      765,
      651
    ],
    [
      810,
      663
    ],
    [
      855,
      483
    ],
    [
      900,
      483
    ],
    [
      945,
      483
    ],
    [
      990,
      480
    ],
    [
      1035,
      478
    ],
    [
      1080,
      477
    ],
    [
      1125,
      478
    ],
    [
      1170,
      479
    ],
    [
      1215,
      519
    ],
    [
      1260,
      478
    ],
    [
      1305,
      479
    ],
    [
      1350,
      497
    ],
    [
      1375,
      497
    ],
    [
      1375,
      767
    ],
    [
      0,
      767
    ],
    [
      0,
      494
    ]
  ]
}